MANIFEST.in
README.md
setup.py
dataset/__init__.py
dataset/dataset_config.py
maxda/__init__.py
maxda.egg-info/PKG-INFO
maxda.egg-info/SOURCES.txt
maxda.egg-info/dependency_links.txt
maxda.egg-info/requires.txt
maxda.egg-info/top_level.txt
maxda.egg-info/zip-safe
maxda/analysis/__init__.py
maxda/analysis/analysis_interface.py
maxda/analysis/common.py
maxda/analysis/da_clean/__init__.py
maxda/analysis/da_clean/ads_spam.py
maxda/analysis/da_clean/all_text_spam.py
maxda/analysis/da_clean/clean_interface.py
maxda/analysis/da_clean/df_distinct.py
maxda/analysis/da_clean/ec_spam.py
maxda/analysis/da_clean/navy_judgment.py
maxda/analysis/da_clean/other_spam.py
maxda/analysis/da_clean/unkeyword_spam.py
maxda/analysis/da_clean/water_spam.py
maxda/analysis/da_extract/__init__.py
maxda/analysis/da_extract/age_format.py
maxda/analysis/da_extract/area.py
maxda/analysis/da_extract/city_rank.py
maxda/analysis/da_extract/datetime_format.py
maxda/analysis/da_extract/gender_format.py
maxda/analysis/da_extract/hastag_extract.py
maxda/analysis/da_extract/number_format.py
maxda/analysis/da_extract/text_format.py
maxda/analysis/da_extract/user_tag.py
maxda/analysis/da_filter/__init__.py
maxda/analysis/da_filter/clean_filter.py
maxda/analysis/da_filter/column_match_filter.py
maxda/analysis/da_filter/filter_interface.py
maxda/analysis/da_pre/__init__.py
maxda/analysis/da_pre/create_data_index.py
maxda/analysis/da_pre/df_format_data.py
maxda/analysis/da_save/__init__.py
maxda/analysis/da_save/more_sheet_save.py
maxda/analysis/da_save/spark_writer.py
maxda/analysis/da_statis/__init__.py
maxda/analysis/da_statis/da_qa_class.py
maxda/analysis/da_tag/Filed_Services.py
maxda/analysis/da_tag/__init__.py
maxda/analysis/da_tag/diatance_tag.py
maxda/analysis/da_tag/label_core.py
maxda/analysis/da_tag/label_dict.py
maxda/analysis/da_tag/label_extract.py
maxda/analysis/da_tag/label_keyword.py
maxda/analysis/da_tag/label_main.py
maxda/analysis/da_tag/label_model.py
maxda/analysis/da_tag/label_util.py
maxda/analysis/da_tag/label_verify.py
maxda/analysis/da_tag/mapping_models.py
maxda/analysis/da_tag/split_tag.py
maxda/analysis/da_tag/tag.py
